{"id": 422, "speciesName": "shellos", "genus": "Sea Slug Pok\u00e9mon", "generation": "generation-iv", "generationLabel": "Gen IV", "color": "purple", "habitat": "Unknown", "shape": "squiggle", "captureRate": 190, "happiness": 70, "growthRate": "medium", "eggGroups": ["indeterminate", "water1"], "hatchCounter": 20, "genderRate": 4, "isLegendary": false, "isMythical": false, "forms": [{"id": 422, "speciesId": 422, "name": "shellos", "image": "/official-artwork/422.png", "isDefault": true, "tag": null, "formFamily": "Standard", "types": ["water"], "abilities": [{"name": "sticky-hold", "hidden": false}, {"name": "storm-drain", "hidden": false}, {"name": "sand-force", "hidden": true}], "stats": [{"name": "hp", "value": 76}, {"name": "attack", "value": 48}, {"name": "defense", "value": 48}, {"name": "special-attack", "value": 57}, {"name": "special-defense", "value": 62}, {"name": "speed", "value": 34}], "baseStatTotal": 325, "height": 0.3, "weight": 6.3, "moveCount": 596, "availableVersionGroups": ["black-2-white-2", "black-white", "brilliant-diamond-shining-pearl", "diamond-pearl", "heartgold-soulsilver", "legends-arceus", "omega-ruby-alpha-sapphire", "platinum", "scarlet-violet", "sun-moon", "sword-shield", "ultra-sun-ultra-moon", "x-y"], "versionGroupMoves": {"black-2-white-2": [{"move": "amnesia", "method": "egg", "level": 0}, {"move": "attract", "method": "machine", "level": 0}, {"move": "blizzard", "method": "machine", "level": 0}, {"move": "brine", "method": "egg", "level": 0}, {"move": "clear-smog", "method": "egg", "level": 0}, {"move": "counter", "method": "egg", "level": 0}, {"move": "curse", "method": "egg", "level": 0}, {"move": "dive", "method": "machine", "level": 0}, {"move": "double-team", "method": "machine", "level": 0}, {"move": "earth-power", "method": "tutor", "level": 0}, {"move": "facade", "method": "machine", "level": 0}, {"move": "fissure", "method": "egg", "level": 0}, {"move": "frustration", "method": "machine", "level": 0}, {"move": "hail", "method": "machine", "level": 0}, {"move": "hidden-power", "method": "machine", "level": 0}, {"move": "ice-beam", "method": "machine", "level": 0}, {"move": "icy-wind", "method": "tutor", "level": 0}, {"move": "memento", "method": "egg", "level": 0}, {"move": "mirror-coat", "method": "egg", "level": 0}, {"move": "mist", "method": "egg", "level": 0}, {"move": "pain-split", "method": "tutor", "level": 0}, {"move": "protect", "method": "machine", "level": 0}, {"move": "rain-dance", "method": "machine", "level": 0}, {"move": "rest", "method": "machine", "level": 0}, {"move": "return", "method": "machine", "level": 0}, {"move": "round", "method": "machine", "level": 0}, {"move": "scald", "method": "machine", "level": 0}, {"move": "sleep-talk", "method": "tutor", "level": 0}, {"move": "sludge", "method": "egg", "level": 0}, {"move": "snore", "method": "tutor", "level": 0}, {"move": "spit-up", "method": "egg", "level": 0}, {"move": "stockpile", "method": "egg", "level": 0}, {"move": "substitute", "method": "machine", "level": 0}, {"move": "surf", "method": "machine", "level": 0}, {"move": "swagger", "method": "machine", "level": 0}, {"move": "swallow", "method": "egg", "level": 0}, {"move": "toxic", "method": "machine", "level": 0}, {"move": "trump-card", "method": "egg", "level": 0}, {"move": "yawn", "method": "egg", "level": 0}, {"move": "mud-slap", "method": "level-up", "level": 1}, {"move": "mud-sport", "method": "level-up", "level": 2}, {"move": "harden", "method": "level-up", "level": 4}, {"move": "water-pulse", "method": "level-up", "level": 7}, {"move": "mud-bomb", "method": "level-up", "level": 11}, {"move": "hidden-power", "method": "level-up", "level": 16}, {"move": "rain-dance", "method": "level-up", "level": 22}, {"move": "body-slam", "method": "level-up", "level": 29}, {"move": "muddy-water", "method": "level-up", "level": 37}, {"move": "recover", "method": "level-up", "level": 46}], "black-white": [{"move": "amnesia", "method": "egg", "level": 0}, {"move": "attract", "method": "machine", "level": 0}, {"move": "blizzard", "method": "machine", "level": 0}, {"move": "brine", "method": "egg", "level": 0}, {"move": "clear-smog", "method": "egg", "level": 0}, {"move": "counter", "method": "egg", "level": 0}, {"move": "curse", "method": "egg", "level": 0}, {"move": "dive", "method": "machine", "level": 0}, {"move": "double-team", "method": "machine", "level": 0}, {"move": "facade", "method": "machine", "level": 0}, {"move": "fissure", "method": "egg", "level": 0}, {"move": "frustration", "method": "machine", "level": 0}, {"move": "hail", "method": "machine", "level": 0}, {"move": "hidden-power", "method": "machine", "level": 0}, {"move": "ice-beam", "method": "machine", "level": 0}, {"move": "memento", "method": "egg", "level": 0}, {"move": "mirror-coat", "method": "egg", "level": 0}, {"move": "mist", "method": "egg", "level": 0}, {"move": "protect", "method": "machine", "level": 0}, {"move": "rain-dance", "method": "machine", "level": 0}, {"move": "rest", "method": "machine", "level": 0}, {"move": "return", "method": "machine", "level": 0}, {"move": "round", "method": "machine", "level": 0}, {"move": "scald", "method": "machine", "level": 0}, {"move": "sludge", "method": "egg", "level": 0}, {"move": "spit-up", "method": "egg", "level": 0}, {"move": "stockpile", "method": "egg", "level": 0}, {"move": "substitute", "method": "machine", "level": 0}, {"move": "surf", "method": "machine", "level": 0}, {"move": "swagger", "method": "machine", "level": 0}, {"move": "swallow", "method": "egg", "level": 0}, {"move": "toxic", "method": "machine", "level": 0}, {"move": "trump-card", "method": "egg", "level": 0}, {"move": "yawn", "method": "egg", "level": 0}, {"move": "mud-slap", "method": "level-up", "level": 1}, {"move": "mud-sport", "method": "level-up", "level": 2}, {"move": "harden", "method": "level-up", "level": 4}, {"move": "water-pulse", "method": "level-up", "level": 7}, {"move": "mud-bomb", "method": "level-up", "level": 11}, {"move": "hidden-power", "method": "level-up", "level": 16}, {"move": "rain-dance", "method": "level-up", "level": 22}, {"move": "body-slam", "method": "level-up", "level": 29}, {"move": "muddy-water", "method": "level-up", "level": 37}, {"move": "recover", "method": "level-up", "level": 46}], "brilliant-diamond-shining-pearl": [{"move": "acid-armor", "method": "egg", "level": 0}, {"move": "amnesia", "method": "egg", "level": 0}, {"move": "attract", "method": "machine", "level": 0}, {"move": "blizzard", "method": "machine", "level": 0}, {"move": "brine", "method": "machine", "level": 0}, {"move": "clear-smog", "method": "egg", "level": 0}, {"move": "counter", "method": "egg", "level": 0}, {"move": "curse", "method": "egg", "level": 0}, {"move": "double-team", "method": "machine", "level": 0}, {"move": "endure", "method": "machine", "level": 0}, {"move": "facade", "method": "machine", "level": 0}, {"move": "fissure", "method": "egg", "level": 0}, {"move": "hail", "method": "machine", "level": 0}, {"move": "ice-beam", "method": "machine", "level": 0}, {"move": "memento", "method": "egg", "level": 0}, {"move": "mirror-coat", "method": "egg", "level": 0}, {"move": "mist", "method": "egg", "level": 0}, {"move": "protect", "method": "machine", "level": 0}, {"move": "rain-dance", "method": "machine", "level": 0}, {"move": "rest", "method": "machine", "level": 0}, {"move": "scald", "method": "machine", "level": 0}, {"move": "sleep-talk", "method": "machine", "level": 0}, {"move": "sludge", "method": "egg", "level": 0}, {"move": "spit-up", "method": "egg", "level": 0}, {"move": "stockpile", "method": "egg", "level": 0}, {"move": "substitute", "method": "machine", "level": 0}, {"move": "surf", "method": "machine", "level": 0}, {"move": "swagger", "method": "machine", "level": 0}, {"move": "swallow", "method": "egg", "level": 0}, {"move": "water-pulse", "method": "machine", "level": 0}, {"move": "yawn", "method": "egg", "level": 0}, {"move": "mud-slap", "method": "level-up", "level": 1}, {"move": "water-gun", "method": "level-up", "level": 1}, {"move": "harden", "method": "level-up", "level": 5}, {"move": "recover", "method": "level-up", "level": 10}, {"move": "water-pulse", "method": "level-up", "level": 15}, {"move": "ancient-power", "method": "level-up", "level": 20}, {"move": "body-slam", "method": "level-up", "level": 25}, {"move": "muddy-water", "method": "level-up", "level": 31}, {"move": "earth-power", "method": "level-up", "level": 35}, {"move": "rain-dance", "method": "level-up", "level": 40}, {"move": "memento", "method": "level-up", "level": 45}], "diamond-pearl": [{"move": "amnesia", "method": "egg", "level": 0}, {"move": "attract", "method": "machine", "level": 0}, {"move": "blizzard", "method": "machine", "level": 0}, {"move": "brine", "method": "machine", "level": 0}, {"move": "captivate", "method": "machine", "level": 0}, {"move": "counter", "method": "egg", "level": 0}, {"move": "curse", "method": "egg", "level": 0}, {"move": "double-team", "method": "machine", "level": 0}, {"move": "endure", "method": "machine", "level": 0}, {"move": "facade", "method": "machine", "level": 0}, {"move": "fissure", "method": "egg", "level": 0}, {"move": "frustration", "method": "machine", "level": 0}, {"move": "hail", "method": "machine", "level": 0}, {"move": "hidden-power", "method": "machine", "level": 0}, {"move": "ice-beam", "method": "machine", "level": 0}, {"move": "memento", "method": "egg", "level": 0}, {"move": "mirror-coat", "method": "egg", "level": 0}, {"move": "natural-gift", "method": "machine", "level": 0}, {"move": "protect", "method": "machine", "level": 0}, {"move": "rain-dance", "method": "machine", "level": 0}, {"move": "rest", "method": "machine", "level": 0}, {"move": "return", "method": "machine", "level": 0}, {"move": "secret-power", "method": "machine", "level": 0}, {"move": "sleep-talk", "method": "machine", "level": 0}, {"move": "spit-up", "method": "egg", "level": 0}, {"move": "stockpile", "method": "egg", "level": 0}, {"move": "substitute", "method": "machine", "level": 0}, {"move": "surf", "method": "machine", "level": 0}, {"move": "swagger", "method": "machine", "level": 0}, {"move": "swallow", "method": "egg", "level": 0}, {"move": "toxic", "method": "machine", "level": 0}, {"move": "water-pulse", "method": "machine", "level": 0}, {"move": "yawn", "method": "egg", "level": 0}, {"move": "mud-slap", "method": "level-up", "level": 1}, {"move": "mud-sport", "method": "level-up", "level": 2}, {"move": "harden", "method": "level-up", "level": 4}, {"move": "water-pulse", "method": "level-up", "level": 7}, {"move": "mud-bomb", "method": "level-up", "level": 11}, {"move": "hidden-power", "method": "level-up", "level": 16}, {"move": "rain-dance", "method": "level-up", "level": 22}, {"move": "body-slam", "method": "level-up", "level": 29}, {"move": "muddy-water", "method": "level-up", "level": 37}, {"move": "recover", "method": "level-up", "level": 46}], "heartgold-soulsilver": [{"move": "amnesia", "method": "egg", "level": 0}, {"move": "ancient-power", "method": "tutor", "level": 0}, {"move": "attract", "method": "machine", "level": 0}, {"move": "blizzard", "method": "machine", "level": 0}, {"move": "brine", "method": "machine", "level": 0}, {"move": "captivate", "method": "machine", "level": 0}, {"move": "counter", "method": "egg", "level": 0}, {"move": "curse", "method": "egg", "level": 0}, {"move": "dive", "method": "tutor", "level": 0}, {"move": "double-team", "method": "machine", "level": 0}, {"move": "earth-power", "method": "tutor", "level": 0}, {"move": "endure", "method": "machine", "level": 0}, {"move": "facade", "method": "machine", "level": 0}, {"move": "fissure", "method": "egg", "level": 0}, {"move": "frustration", "method": "machine", "level": 0}, {"move": "hail", "method": "machine", "level": 0}, {"move": "headbutt", "method": "tutor", "level": 0}, {"move": "hidden-power", "method": "machine", "level": 0}, {"move": "ice-beam", "method": "machine", "level": 0}, {"move": "icy-wind", "method": "tutor", "level": 0}, {"move": "memento", "method": "egg", "level": 0}, {"move": "mirror-coat", "method": "egg", "level": 0}, {"move": "mud-slap", "method": "tutor", "level": 0}, {"move": "natural-gift", "method": "machine", "level": 0}, {"move": "pain-split", "method": "tutor", "level": 0}, {"move": "protect", "method": "machine", "level": 0}, {"move": "rain-dance", "method": "machine", "level": 0}, {"move": "rest", "method": "machine", "level": 0}, {"move": "return", "method": "machine", "level": 0}, {"move": "secret-power", "method": "machine", "level": 0}, {"move": "sleep-talk", "method": "machine", "level": 0}, {"move": "sludge", "method": "egg", "level": 0}, {"move": "snore", "method": "tutor", "level": 0}, {"move": "spit-up", "method": "egg", "level": 0}, {"move": "stockpile", "method": "egg", "level": 0}, {"move": "string-shot", "method": "tutor", "level": 0}, {"move": "substitute", "method": "machine", "level": 0}, {"move": "surf", "method": "machine", "level": 0}, {"move": "swagger", "method": "machine", "level": 0}, {"move": "swallow", "method": "egg", "level": 0}, {"move": "toxic", "method": "machine", "level": 0}, {"move": "trump-card", "method": "egg", "level": 0}, {"move": "water-pulse", "method": "machine", "level": 0}, {"move": "whirlpool", "method": "machine", "level": 0}, {"move": "yawn", "method": "egg", "level": 0}, {"move": "mud-slap", "method": "level-up", "level": 1}, {"move": "mud-sport", "method": "level-up", "level": 2}, {"move": "harden", "method": "level-up", "level": 4}, {"move": "water-pulse", "method": "level-up", "level": 7}, {"move": "mud-bomb", "method": "level-up", "level": 11}, {"move": "hidden-power", "method": "level-up", "level": 16}, {"move": "rain-dance", "method": "level-up", "level": 22}, {"move": "body-slam", "method": "level-up", "level": 29}, {"move": "muddy-water", "method": "level-up", "level": 37}, {"move": "recover", "method": "level-up", "level": 46}], "legends-arceus": [{"move": "mud-slap", "method": "level-up", "level": 1}, {"move": "tackle", "method": "level-up", "level": 5}, {"move": "water-pulse", "method": "level-up", "level": 9}, {"move": "ancient-power", "method": "level-up", "level": 15}, {"move": "mud-bomb", "method": "level-up", "level": 21}, {"move": "earth-power", "method": "level-up", "level": 29}, {"move": "recover", "method": "level-up", "level": 37}, {"move": "hydro-pump", "method": "level-up", "level": 47}], "omega-ruby-alpha-sapphire": [{"move": "acid-armor", "method": "egg", "level": 0}, {"move": "amnesia", "method": "egg", "level": 0}, {"move": "attract", "method": "machine", "level": 0}, {"move": "blizzard", "method": "machine", "level": 0}, {"move": "brine", "method": "egg", "level": 0}, {"move": "clear-smog", "method": "egg", "level": 0}, {"move": "confide", "method": "machine", "level": 0}, {"move": "counter", "method": "egg", "level": 0}, {"move": "curse", "method": "egg", "level": 0}, {"move": "dive", "method": "machine", "level": 0}, {"move": "double-team", "method": "machine", "level": 0}, {"move": "earth-power", "method": "tutor", "level": 0}, {"move": "facade", "method": "machine", "level": 0}, {"move": "fissure", "method": "egg", "level": 0}, {"move": "frustration", "method": "machine", "level": 0}, {"move": "hail", "method": "machine", "level": 0}, {"move": "hidden-power", "method": "machine", "level": 0}, {"move": "ice-beam", "method": "machine", "level": 0}, {"move": "icy-wind", "method": "tutor", "level": 0}, {"move": "infestation", "method": "machine", "level": 0}, {"move": "memento", "method": "egg", "level": 0}, {"move": "mirror-coat", "method": "egg", "level": 0}, {"move": "mist", "method": "egg", "level": 0}, {"move": "pain-split", "method": "tutor", "level": 0}, {"move": "protect", "method": "machine", "level": 0}, {"move": "rain-dance", "method": "machine", "level": 0}, {"move": "rest", "method": "machine", "level": 0}, {"move": "return", "method": "machine", "level": 0}, {"move": "round", "method": "machine", "level": 0}, {"move": "scald", "method": "machine", "level": 0}, {"move": "secret-power", "method": "machine", "level": 0}, {"move": "sleep-talk", "method": "machine", "level": 0}, {"move": "sludge", "method": "egg", "level": 0}, {"move": "snore", "method": "tutor", "level": 0}, {"move": "spit-up", "method": "egg", "level": 0}, {"move": "stockpile", "method": "egg", "level": 0}, {"move": "substitute", "method": "machine", "level": 0}, {"move": "surf", "method": "machine", "level": 0}, {"move": "swagger", "method": "machine", "level": 0}, {"move": "swallow", "method": "egg", "level": 0}, {"move": "toxic", "method": "machine", "level": 0}, {"move": "trump-card", "method": "egg", "level": 0}, {"move": "water-pulse", "method": "tutor", "level": 0}, {"move": "yawn", "method": "egg", "level": 0}, {"move": "mud-slap", "method": "level-up", "level": 1}, {"move": "mud-sport", "method": "level-up", "level": 2}, {"move": "harden", "method": "level-up", "level": 4}, {"move": "water-pulse", "method": "level-up", "level": 7}, {"move": "mud-bomb", "method": "level-up", "level": 11}, {"move": "hidden-power", "method": "level-up", "level": 16}, {"move": "rain-dance", "method": "level-up", "level": 22}, {"move": "body-slam", "method": "level-up", "level": 29}, {"move": "muddy-water", "method": "level-up", "level": 37}, {"move": "recover", "method": "level-up", "level": 46}], "platinum": [{"move": "amnesia", "method": "egg", "level": 0}, {"move": "ancient-power", "method": "tutor", "level": 0}, {"move": "attract", "method": "machine", "level": 0}, {"move": "blizzard", "method": "machine", "level": 0}, {"move": "brine", "method": "machine", "level": 0}, {"move": "captivate", "method": "machine", "level": 0}, {"move": "counter", "method": "egg", "level": 0}, {"move": "curse", "method": "egg", "level": 0}, {"move": "dive", "method": "tutor", "level": 0}, {"move": "double-team", "method": "machine", "level": 0}, {"move": "earth-power", "method": "tutor", "level": 0}, {"move": "endure", "method": "machine", "level": 0}, {"move": "facade", "method": "machine", "level": 0}, {"move": "fissure", "method": "egg", "level": 0}, {"move": "frustration", "method": "machine", "level": 0}, {"move": "hail", "method": "machine", "level": 0}, {"move": "hidden-power", "method": "machine", "level": 0}, {"move": "ice-beam", "method": "machine", "level": 0}, {"move": "icy-wind", "method": "tutor", "level": 0}, {"move": "memento", "method": "egg", "level": 0}, {"move": "mirror-coat", "method": "egg", "level": 0}, {"move": "mud-slap", "method": "tutor", "level": 0}, {"move": "natural-gift", "method": "machine", "level": 0}, {"move": "protect", "method": "machine", "level": 0}, {"move": "rain-dance", "method": "machine", "level": 0}, {"move": "rest", "method": "machine", "level": 0}, {"move": "return", "method": "machine", "level": 0}, {"move": "secret-power", "method": "machine", "level": 0}, {"move": "sleep-talk", "method": "machine", "level": 0}, {"move": "snore", "method": "tutor", "level": 0}, {"move": "spit-up", "method": "egg", "level": 0}, {"move": "stockpile", "method": "egg", "level": 0}, {"move": "substitute", "method": "machine", "level": 0}, {"move": "surf", "method": "machine", "level": 0}, {"move": "swagger", "method": "machine", "level": 0}, {"move": "swallow", "method": "egg", "level": 0}, {"move": "toxic", "method": "machine", "level": 0}, {"move": "water-pulse", "method": "machine", "level": 0}, {"move": "yawn", "method": "egg", "level": 0}, {"move": "mud-slap", "method": "level-up", "level": 1}, {"move": "mud-sport", "method": "level-up", "level": 2}, {"move": "harden", "method": "level-up", "level": 4}, {"move": "water-pulse", "method": "level-up", "level": 7}, {"move": "mud-bomb", "method": "level-up", "level": 11}, {"move": "hidden-power", "method": "level-up", "level": 16}, {"move": "rain-dance", "method": "level-up", "level": 22}, {"move": "body-slam", "method": "level-up", "level": 29}, {"move": "muddy-water", "method": "level-up", "level": 37}, {"move": "recover", "method": "level-up", "level": 46}], "scarlet-violet": [{"move": "acid-armor", "method": "egg", "level": 0}, {"move": "amnesia", "method": "machine", "level": 0}, {"move": "blizzard", "method": "machine", "level": 0}, {"move": "body-slam", "method": "machine", "level": 0}, {"move": "bulldoze", "method": "machine", "level": 0}, {"move": "chilling-water", "method": "machine", "level": 0}, {"move": "clear-smog", "method": "egg", "level": 0}, {"move": "counter", "method": "egg", "level": 0}, {"move": "curse", "method": "egg", "level": 0}, {"move": "curse", "method": "machine", "level": 0}, {"move": "earth-power", "method": "machine", "level": 0}, {"move": "endure", "method": "machine", "level": 0}, {"move": "facade", "method": "machine", "level": 0}, {"move": "helping-hand", "method": "machine", "level": 0}, {"move": "hydro-pump", "method": "machine", "level": 0}, {"move": "ice-beam", "method": "machine", "level": 0}, {"move": "icy-wind", "method": "machine", "level": 0}, {"move": "liquidation", "method": "machine", "level": 0}, {"move": "mirror-coat", "method": "egg", "level": 0}, {"move": "mist", "method": "egg", "level": 0}, {"move": "mud-shot", "method": "machine", "level": 0}, {"move": "mud-slap", "method": "machine", "level": 0}, {"move": "muddy-water", "method": "machine", "level": 0}, {"move": "pain-split", "method": "machine", "level": 0}, {"move": "protect", "method": "machine", "level": 0}, {"move": "rain-dance", "method": "machine", "level": 0}, {"move": "rest", "method": "machine", "level": 0}, {"move": "rock-slide", "method": "machine", "level": 0}, {"move": "rock-tomb", "method": "machine", "level": 0}, {"move": "sandstorm", "method": "machine", "level": 0}, {"move": "skitter-smack", "method": "machine", "level": 0}, {"move": "sleep-talk", "method": "machine", "level": 0}, {"move": "sludge", "method": "egg", "level": 0}, {"move": "snowscape", "method": "machine", "level": 0}, {"move": "spit-up", "method": "egg", "level": 0}, {"move": "stealth-rock", "method": "machine", "level": 0}, {"move": "stockpile", "method": "egg", "level": 0}, {"move": "stone-edge", "method": "machine", "level": 0}, {"move": "substitute", "method": "machine", "level": 0}, {"move": "surf", "method": "machine", "level": 0}, {"move": "swallow", "method": "egg", "level": 0}, {"move": "take-down", "method": "machine", "level": 0}, {"move": "tera-blast", "method": "machine", "level": 0}, {"move": "water-pulse", "method": "machine", "level": 0}, {"move": "waterfall", "method": "machine", "level": 0}, {"move": "whirlpool", "method": "machine", "level": 0}, {"move": "yawn", "method": "egg", "level": 0}, {"move": "mud-slap", "method": "level-up", "level": 1}, {"move": "water-gun", "method": "level-up", "level": 1}, {"move": "harden", "method": "level-up", "level": 5}, {"move": "recover", "method": "level-up", "level": 10}, {"move": "water-pulse", "method": "level-up", "level": 15}, {"move": "ancient-power", "method": "level-up", "level": 20}, {"move": "body-slam", "method": "level-up", "level": 25}, {"move": "muddy-water", "method": "level-up", "level": 31}, {"move": "earth-power", "method": "level-up", "level": 35}, {"move": "rain-dance", "method": "level-up", "level": 40}, {"move": "memento", "method": "level-up", "level": 45}], "sun-moon": [{"move": "acid-armor", "method": "egg", "level": 0}, {"move": "amnesia", "method": "egg", "level": 0}, {"move": "attract", "method": "machine", "level": 0}, {"move": "blizzard", "method": "machine", "level": 0}, {"move": "brine", "method": "egg", "level": 0}, {"move": "clear-smog", "method": "egg", "level": 0}, {"move": "confide", "method": "machine", "level": 0}, {"move": "counter", "method": "egg", "level": 0}, {"move": "curse", "method": "egg", "level": 0}, {"move": "double-team", "method": "machine", "level": 0}, {"move": "facade", "method": "machine", "level": 0}, {"move": "fissure", "method": "egg", "level": 0}, {"move": "frustration", "method": "machine", "level": 0}, {"move": "hail", "method": "machine", "level": 0}, {"move": "hidden-power", "method": "machine", "level": 0}, {"move": "ice-beam", "method": "machine", "level": 0}, {"move": "infestation", "method": "machine", "level": 0}, {"move": "memento", "method": "egg", "level": 0}, {"move": "mirror-coat", "method": "egg", "level": 0}, {"move": "mist", "method": "egg", "level": 0}, {"move": "protect", "method": "machine", "level": 0}, {"move": "rain-dance", "method": "machine", "level": 0}, {"move": "rest", "method": "machine", "level": 0}, {"move": "return", "method": "machine", "level": 0}, {"move": "round", "method": "machine", "level": 0}, {"move": "scald", "method": "machine", "level": 0}, {"move": "sleep-talk", "method": "machine", "level": 0}, {"move": "sludge", "method": "egg", "level": 0}, {"move": "spit-up", "method": "egg", "level": 0}, {"move": "stockpile", "method": "egg", "level": 0}, {"move": "substitute", "method": "machine", "level": 0}, {"move": "surf", "method": "machine", "level": 0}, {"move": "swagger", "method": "machine", "level": 0}, {"move": "swallow", "method": "egg", "level": 0}, {"move": "toxic", "method": "machine", "level": 0}, {"move": "trump-card", "method": "egg", "level": 0}, {"move": "yawn", "method": "egg", "level": 0}, {"move": "mud-slap", "method": "level-up", "level": 1}, {"move": "mud-sport", "method": "level-up", "level": 2}, {"move": "harden", "method": "level-up", "level": 4}, {"move": "water-pulse", "method": "level-up", "level": 7}, {"move": "mud-bomb", "method": "level-up", "level": 11}, {"move": "hidden-power", "method": "level-up", "level": 16}, {"move": "rain-dance", "method": "level-up", "level": 22}, {"move": "body-slam", "method": "level-up", "level": 29}, {"move": "muddy-water", "method": "level-up", "level": 37}, {"move": "recover", "method": "level-up", "level": 46}], "sword-shield": [{"move": "acid-armor", "method": "egg", "level": 0}, {"move": "amnesia", "method": "machine", "level": 0}, {"move": "attract", "method": "machine", "level": 0}, {"move": "blizzard", "method": "machine", "level": 0}, {"move": "body-slam", "method": "machine", "level": 0}, {"move": "brine", "method": "machine", "level": 0}, {"move": "clear-smog", "method": "egg", "level": 0}, {"move": "counter", "method": "egg", "level": 0}, {"move": "curse", "method": "egg", "level": 0}, {"move": "dive", "method": "machine", "level": 0}, {"move": "earth-power", "method": "machine", "level": 0}, {"move": "endure", "method": "machine", "level": 0}, {"move": "facade", "method": "machine", "level": 0}, {"move": "hail", "method": "machine", "level": 0}, {"move": "hydro-pump", "method": "machine", "level": 0}, {"move": "ice-beam", "method": "machine", "level": 0}, {"move": "icy-wind", "method": "machine", "level": 0}, {"move": "mirror-coat", "method": "egg", "level": 0}, {"move": "mist", "method": "egg", "level": 0}, {"move": "mud-shot", "method": "machine", "level": 0}, {"move": "muddy-water", "method": "machine", "level": 0}, {"move": "protect", "method": "machine", "level": 0}, {"move": "rain-dance", "method": "machine", "level": 0}, {"move": "rest", "method": "machine", "level": 0}, {"move": "round", "method": "machine", "level": 0}, {"move": "scald", "method": "machine", "level": 0}, {"move": "skitter-smack", "method": "tutor", "level": 0}, {"move": "sleep-talk", "method": "machine", "level": 0}, {"move": "sludge", "method": "egg", "level": 0}, {"move": "snore", "method": "machine", "level": 0}, {"move": "spit-up", "method": "egg", "level": 0}, {"move": "stockpile", "method": "egg", "level": 0}, {"move": "substitute", "method": "machine", "level": 0}, {"move": "surf", "method": "machine", "level": 0}, {"move": "swallow", "method": "egg", "level": 0}, {"move": "whirlpool", "method": "machine", "level": 0}, {"move": "yawn", "method": "egg", "level": 0}, {"move": "mud-slap", "method": "level-up", "level": 1}, {"move": "water-gun", "method": "level-up", "level": 1}, {"move": "harden", "method": "level-up", "level": 5}, {"move": "recover", "method": "level-up", "level": 10}, {"move": "water-pulse", "method": "level-up", "level": 15}, {"move": "ancient-power", "method": "level-up", "level": 20}, {"move": "body-slam", "method": "level-up", "level": 25}, {"move": "muddy-water", "method": "level-up", "level": 31}, {"move": "earth-power", "method": "level-up", "level": 35}, {"move": "rain-dance", "method": "level-up", "level": 40}, {"move": "memento", "method": "level-up", "level": 45}], "ultra-sun-ultra-moon": [{"move": "acid-armor", "method": "egg", "level": 0}, {"move": "amnesia", "method": "egg", "level": 0}, {"move": "attract", "method": "machine", "level": 0}, {"move": "blizzard", "method": "machine", "level": 0}, {"move": "brine", "method": "egg", "level": 0}, {"move": "clear-smog", "method": "egg", "level": 0}, {"move": "confide", "method": "machine", "level": 0}, {"move": "counter", "method": "egg", "level": 0}, {"move": "curse", "method": "egg", "level": 0}, {"move": "double-team", "method": "machine", "level": 0}, {"move": "earth-power", "method": "tutor", "level": 0}, {"move": "facade", "method": "machine", "level": 0}, {"move": "fissure", "method": "egg", "level": 0}, {"move": "frustration", "method": "machine", "level": 0}, {"move": "hail", "method": "machine", "level": 0}, {"move": "hidden-power", "method": "machine", "level": 0}, {"move": "ice-beam", "method": "machine", "level": 0}, {"move": "icy-wind", "method": "tutor", "level": 0}, {"move": "infestation", "method": "machine", "level": 0}, {"move": "memento", "method": "egg", "level": 0}, {"move": "mirror-coat", "method": "egg", "level": 0}, {"move": "mist", "method": "egg", "level": 0}, {"move": "pain-split", "method": "tutor", "level": 0}, {"move": "protect", "method": "machine", "level": 0}, {"move": "rain-dance", "method": "machine", "level": 0}, {"move": "rest", "method": "machine", "level": 0}, {"move": "return", "method": "machine", "level": 0}, {"move": "round", "method": "machine", "level": 0}, {"move": "scald", "method": "machine", "level": 0}, {"move": "sleep-talk", "method": "machine", "level": 0}, {"move": "sludge", "method": "egg", "level": 0}, {"move": "snore", "method": "tutor", "level": 0}, {"move": "spit-up", "method": "egg", "level": 0}, {"move": "stockpile", "method": "egg", "level": 0}, {"move": "substitute", "method": "machine", "level": 0}, {"move": "surf", "method": "machine", "level": 0}, {"move": "swagger", "method": "machine", "level": 0}, {"move": "swallow", "method": "egg", "level": 0}, {"move": "toxic", "method": "machine", "level": 0}, {"move": "trump-card", "method": "egg", "level": 0}, {"move": "water-pulse", "method": "tutor", "level": 0}, {"move": "yawn", "method": "egg", "level": 0}, {"move": "mud-slap", "method": "level-up", "level": 1}, {"move": "mud-sport", "method": "level-up", "level": 2}, {"move": "harden", "method": "level-up", "level": 4}, {"move": "water-pulse", "method": "level-up", "level": 7}, {"move": "mud-bomb", "method": "level-up", "level": 11}, {"move": "hidden-power", "method": "level-up", "level": 16}, {"move": "rain-dance", "method": "level-up", "level": 22}, {"move": "body-slam", "method": "level-up", "level": 29}, {"move": "muddy-water", "method": "level-up", "level": 37}, {"move": "recover", "method": "level-up", "level": 46}], "x-y": [{"move": "acid-armor", "method": "egg", "level": 0}, {"move": "amnesia", "method": "egg", "level": 0}, {"move": "attract", "method": "machine", "level": 0}, {"move": "blizzard", "method": "machine", "level": 0}, {"move": "brine", "method": "egg", "level": 0}, {"move": "clear-smog", "method": "egg", "level": 0}, {"move": "confide", "method": "machine", "level": 0}, {"move": "counter", "method": "egg", "level": 0}, {"move": "curse", "method": "egg", "level": 0}, {"move": "double-team", "method": "machine", "level": 0}, {"move": "facade", "method": "machine", "level": 0}, {"move": "fissure", "method": "egg", "level": 0}, {"move": "frustration", "method": "machine", "level": 0}, {"move": "hail", "method": "machine", "level": 0}, {"move": "hidden-power", "method": "machine", "level": 0}, {"move": "ice-beam", "method": "machine", "level": 0}, {"move": "infestation", "method": "machine", "level": 0}, {"move": "memento", "method": "egg", "level": 0}, {"move": "mirror-coat", "method": "egg", "level": 0}, {"move": "mist", "method": "egg", "level": 0}, {"move": "protect", "method": "machine", "level": 0}, {"move": "rain-dance", "method": "machine", "level": 0}, {"move": "rest", "method": "machine", "level": 0}, {"move": "return", "method": "machine", "level": 0}, {"move": "round", "method": "machine", "level": 0}, {"move": "scald", "method": "machine", "level": 0}, {"move": "sleep-talk", "method": "machine", "level": 0}, {"move": "sludge", "method": "egg", "level": 0}, {"move": "spit-up", "method": "egg", "level": 0}, {"move": "stockpile", "method": "egg", "level": 0}, {"move": "substitute", "method": "machine", "level": 0}, {"move": "surf", "method": "machine", "level": 0}, {"move": "swagger", "method": "machine", "level": 0}, {"move": "swallow", "method": "egg", "level": 0}, {"move": "toxic", "method": "machine", "level": 0}, {"move": "trump-card", "method": "egg", "level": 0}, {"move": "yawn", "method": "egg", "level": 0}, {"move": "mud-slap", "method": "level-up", "level": 1}, {"move": "mud-sport", "method": "level-up", "level": 2}, {"move": "harden", "method": "level-up", "level": 4}, {"move": "water-pulse", "method": "level-up", "level": 7}, {"move": "mud-bomb", "method": "level-up", "level": 11}, {"move": "hidden-power", "method": "level-up", "level": 16}, {"move": "rain-dance", "method": "level-up", "level": 22}, {"move": "body-slam", "method": "level-up", "level": 29}, {"move": "muddy-water", "method": "level-up", "level": 37}, {"move": "recover", "method": "level-up", "level": 46}]}}], "defaultFormId": 422, "versionEntries": [{"version": "alpha-sapphire", "text": "Its shape and coloration vary, depending on its habitat."}, {"version": "black", "text": "Beware of pushing strongly on its squishy body, as it makes a mysterious purple fluid ooze out."}, {"version": "black-2", "text": "Beware of pushing strongly on its squishy body, as it makes a mysterious purple fluid ooze out."}, {"version": "diamond", "text": "Its colors and shapes differ from region to region. In the Sinnoh region, two types are confirmed."}, {"version": "heartgold", "text": "Its shape and coloration vary, depending on its habitat."}, {"version": "legends-arceus", "text": "Found in abundance on seashores bordering warm waters. Shellos are unexpectedly friendly and will crawl toward any person they see. Take care not to get coated in mucus!"}, {"version": "moon", "text": "Purple mucus sticks to the hands of anyone who touches it. Take care, as the substance is troublesome to wash off."}, {"version": "omega-ruby", "text": "Beware of pushing strongly on its squishy body, as it makes a mysterious purple fluid ooze out."}, {"version": "pearl", "text": "It lives along bodies of water. Its body shape has changed to suit its habitat."}, {"version": "platinum", "text": "Beware of pushing strongly on its squishy body, as it makes a mysterious purple fluid ooze out."}, {"version": "shield", "text": "Subjecting this Pok\u00e9mon to a strong force causes it to secrete a strange purple fluid. Though harmless, the fluid is awfully sticky."}, {"version": "soulsilver", "text": "Its shape and coloration vary, depending on its habitat."}, {"version": "sun", "text": "For the most part, it makes its home along the seashore. Its color and form differ according to its habitat and the quality of its food."}, {"version": "sword", "text": "This Pok\u00e9mon\u2019s habitat shapes its physique. According to some theories, life in warm ocean waters causes this variation to develop."}, {"version": "ultra-moon", "text": "When it senses danger, a purple liquid oozes out of it. The liquid is thought to be something like greasy sweat."}, {"version": "ultra-sun", "text": "While they normally live in the sea, they can function on land, too, until their skin dries out."}, {"version": "white", "text": "Beware of pushing strongly on its squishy body, as it makes a mysterious purple fluid ooze out."}, {"version": "white-2", "text": "Beware of pushing strongly on its squishy body, as it makes a mysterious purple fluid ooze out."}, {"version": "x", "text": "Beware of pushing strongly on its squishy body, as it makes a mysterious purple fluid ooze out."}, {"version": "y", "text": "Its shape and coloration vary, depending on its habitat."}], "entryGameVersions": ["alpha-sapphire", "black", "black-2", "diamond", "heartgold", "legends-arceus", "moon", "omega-ruby", "pearl", "platinum", "shield", "soulsilver", "sun", "sword", "ultra-moon", "ultra-sun", "white", "white-2", "x", "y"], "moveGameGroups": ["black-2-white-2", "black-white", "brilliant-diamond-shining-pearl", "diamond-pearl", "heartgold-soulsilver", "legends-arceus", "omega-ruby-alpha-sapphire", "platinum", "scarlet-violet", "sun-moon", "sword-shield", "ultra-sun-ultra-moon", "x-y"], "evolutionRows": [{"stage": 1, "name": "shellos"}, {"stage": 2, "name": "gastrodon"}]}